dfa_identify/__init__.py
dfa_identify/active.py
dfa_identify/concept_class_restrictions.py
dfa_identify/decomposed.py
dfa_identify/encoding.py
dfa_identify/graphs.py
dfa_identify/identify.py
dfa_identify-3.13.0.dist-info/LICENSE
dfa_identify-3.13.0.dist-info/METADATA
dfa_identify-3.13.0.dist-info/WHEEL
dfa_identify-3.13.0.dist-info/RECORD
