Metadata-Version: 2.1
Name: dfa_identify
Version: 3.13.0
Summary: Python library for identifying (learning) DFAs (automata) from labeled examples.
Home-page: https://github.com/mvcisback/dfa-identify
License: MIT
Author: Marcell Vazquez-Chanlatte
Author-email: mvc@linux.com
Requires-Python: >=3.9,<4.0
Classifier: License :: OSI Approved :: MIT License
Classifier: Programming Language :: Python :: 3
Classifier: Programming Language :: Python :: 3.9
Classifier: Programming Language :: Python :: 3.10
Classifier: Programming Language :: Python :: 3.11
Classifier: Programming Language :: Python :: 3.12
Requires-Dist: attrs (>=22.0.0)
Requires-Dist: bidict (>=0.22,<0.23)
Requires-Dist: dfa (>=4,<5)
Requires-Dist: funcy (>=1.15,<2.0)
Requires-Dist: more-itertools (>=9,<10)
Requires-Dist: networkx (>=3,<4)
Requires-Dist: python-sat (==1.*)
Project-URL: Repository, https://github.com/mvcisback/dfa-identify
